LICENSE
MANIFEST.in
README.md
requirements.txt
setup.py
hooks4git/.hooks4git.ini
hooks4git/__init__.py
hooks4git/app.py
hooks4git/build.info
hooks4git/console.py
hooks4git/hook.py
hooks4git/tools.py
hooks4git.egg-info/PKG-INFO
hooks4git.egg-info/SOURCES.txt
hooks4git.egg-info/dependency_links.txt
hooks4git.egg-info/entry_points.txt
hooks4git.egg-info/requires.txt
hooks4git.egg-info/top_level.txt
hooks4git.egg-info/zip-safe
hooks4git/git/hooks/applypatch-msg
hooks4git/git/hooks/commit-msg
hooks4git/git/hooks/fsmonitor-watchman
hooks4git/git/hooks/post-applypatch
hooks4git/git/hooks/post-checkout
hooks4git/git/hooks/post-commit
hooks4git/git/hooks/post-merge
hooks4git/git/hooks/post-receive
hooks4git/git/hooks/post-rewrite
hooks4git/git/hooks/post-update
hooks4git/git/hooks/pre-applypatch
hooks4git/git/hooks/pre-auto-gc
hooks4git/git/hooks/pre-commit
hooks4git/git/hooks/pre-push
hooks4git/git/hooks/pre-rebase
hooks4git/git/hooks/pre-receive
hooks4git/git/hooks/prepare-commit-msg
hooks4git/git/hooks/push-to-checkout
hooks4git/git/hooks/sendemail-validate
hooks4git/git/hooks/update
hooks4git/h4g/__init__.py
hooks4git/h4g/check_branch_name
hooks4git/h4g/check_branch_name.sh
hooks4git/h4g/get_staged_files