Metadata-Version: 2.1
Name: hooks4git
Version: 0.4.289
Summary: Extensible Hook System for GIT
Home-page: https://github.com/lovato/hooks4git
Author: Marco Lovato
Author-email: maglovato@gmail.com
License: MIT
Download-URL: https://github.com/lovato/hooks4git/tarball/0.4.289
Platform: any
Provides-Extra: dev
